cfigo.cp311-win_amd64.pyd
figo.py
pyfigo-0.1.5.dist-info/licenses/LICENSE
pyfigo-0.1.5.dist-info/METADATA
pyfigo-0.1.5.dist-info/WHEEL
pyfigo-0.1.5.dist-info/entry_points.txt
pyfigo-0.1.5.dist-info/top_level.txt
pyfigo-0.1.5.dist-info/RECORD
