Metadata-Version: 2.4
Name: pyfigo
Version: 0.1.5
Summary: Get the OBJECT keyword from a fits file
Author-email: João Faria <joao.faria@unige.ch>
Requires-Python: >=3.11
License-File: LICENSE
Dynamic: license-file
